project/__init__.py
project/folder_reader.py
project/folder_summary.py
project/folder_visualizer.py
project/read.py
project_reader-0.0.3.dist-info/LICENSE
project_reader-0.0.3.dist-info/METADATA
project_reader-0.0.3.dist-info/WHEEL
project_reader-0.0.3.dist-info/top_level.txt
project_reader-0.0.3.dist-info/RECORD
