Metadata-Version: 2.1
Name: project-reader
Version: 0.0.3
Summary: Read and analyse the files in your projects.
Home-page: https://github.com/muremwa/Project-Reader
Author: Muremwa
Author-email: danmburu254@gmail.com
License: UNKNOWN
Platform: UNKNOWN
Classifier: Programming Language :: Python :: 3
Classifier: License :: OSI Approved :: MIT License
Classifier: Operating System :: OS Independent
Requires-Python: >=3.6
License-File: LICENSE
